Metadata-Version: 2.1
Name: rand-omata
Version: 0.3.3
Summary: It's a matrix generator which can return random data matrix which can be used for data science!
Home-page: https://github.com/Major-Manu/rand-omata.git
Author: Major Manu
Author-email: majors00production@gmail.com
Keywords: matrix
Classifier: Development Status :: 5 - Production/Stable
Classifier: Intended Audience :: Developers
Classifier: Operating System :: Microsoft :: Windows :: Windows 11
Classifier: Programming Language :: Python :: 3
